setup.py
rest_confidence_client_python.egg-info/PKG-INFO
rest_confidence_client_python.egg-info/SOURCES.txt
rest_confidence_client_python.egg-info/dependency_links.txt
rest_confidence_client_python.egg-info/top_level.txt
restconfidence/ConfigurationResolver.py
restconfidence/__init__.py