Metadata-Version: 1.0
Name: rest-confidence-client-python
Version: 1.0.0
Summary: Python client for the rest-confidence configuration server
Home-page: https://github.com/palmerabollo/rest-confidence-client-python
Author: Guido Garcia
Author-email: palmerabollo@gmail.com
License: MIT
Platform: UNKNOWN
